mgsc/__init__.py
mgsc/mgsc.py
mgsc/blueprints/__init__.py
mgsc/blueprints/namespaces.py
mgsc/blueprints/repositories.py
mgsc/service/__init__.py
mgsc/service/gitea.py
mgsc/service/github.py
mgsc/service/gitlab.py
mgsc/service/service.py
mgsc/service/session.py
mgsc/service/stash.py
mgsc-0.1.2.dist-info/AUTHORS.rst
mgsc-0.1.2.dist-info/LICENSE
mgsc-0.1.2.dist-info/METADATA
mgsc-0.1.2.dist-info/WHEEL
mgsc-0.1.2.dist-info/top_level.txt
mgsc-0.1.2.dist-info/RECORD
