Metadata-Version: 2.1
Name: mgsc
Version: 0.1.2
Summary: Multi git server client. A basic client for multiple git servers like GItlab, Github and Gitea
Home-page: https://github.com/amritanshu-pandey/mgsc
Author: Amritanshu Pandey
Author-email: email@amritanshu.in
License: MIT license
Keywords: mgsc
Platform: UNKNOWN
Classifier: Development Status :: 2 - Pre-Alpha
Classifier: Intended Audience :: Developers
Classifier: License :: OSI Approved :: MIT License
Classifier: Natural Language :: English
Classifier: Programming Language :: Python :: 3
Classifier: Programming Language :: Python :: 3.5
Classifier: Programming Language :: Python :: 3.6
Classifier: Programming Language :: Python :: 3.7
Classifier: Programming Language :: Python :: 3.8
Requires-Python: >=3.5
License-File: LICENSE
License-File: AUTHORS.rst
Requires-Dist: GitPython
Requires-Dist: requests
